README.txt
setup.py
ost/__init__.py
ost/znap2/__init__.py
ost/znap2/script.py
ost/znap2/storage.py
ost_znap2.egg-info/PKG-INFO
ost_znap2.egg-info/SOURCES.txt
ost_znap2.egg-info/dependency_links.txt
ost_znap2.egg-info/entry_points.txt
ost_znap2.egg-info/namespace_packages.txt
ost_znap2.egg-info/requires.txt
ost_znap2.egg-info/top_level.txt
ost_znap2.egg-info/zip-safe