Metadata-Version: 1.0
Name: ost-znap2
Version: 1.0b
Summary: ZoDB snapshotter library and script
Home-page: https://bitbucket.org/kvas/ost-znap2
Author: Vasily Kuznetsov
Author-email: kvas.it@gmail.com
License: MIT
Platform: UNKNOWN
Classifier: Development Status :: 4 - Beta
Classifier: License :: OSI Approved :: MIT License
Classifier: Programming Language :: Python
